MANIFEST.in
README.md
setup.py
pvlv_commando/__init__.py
pvlv_commando/pvlv_commando.py
pvlv_commando.egg-info/PKG-INFO
pvlv_commando.egg-info/SOURCES.txt
pvlv_commando.egg-info/dependency_links.txt
pvlv_commando.egg-info/top_level.txt
pvlv_commando/commando/__init__.py
pvlv_commando/commando/command_descriptor.py
pvlv_commando/commando/command_importer.py
pvlv_commando/commando/command_structure_reader.py
pvlv_commando/commando/shortcut_reader.py
pvlv_commando/commando/auto_command_creation/__init__.py
pvlv_commando/commando/auto_command_creation/start_command.py
pvlv_commando/commando/auto_command_creation/command_example/__init__.py
pvlv_commando/commando/auto_command_creation/command_example/command_example.json
pvlv_commando/commando/auto_command_creation/command_example/command_example.py
pvlv_commando/commando/modules/__init__.py
pvlv_commando/commando/modules/base_command_reader.py
pvlv_commando/configurations/__init__.py
pvlv_commando/configurations/configuration.py
pvlv_commando/exceptions/__init__.py
pvlv_commando/exceptions/command_error_report.py
pvlv_commando/exceptions/errors_exceptions.py
pvlv_commando/exceptions/permissions_exceptions.py
pvlv_commando/languages/__init__.py
pvlv_commando/languages/languages_handler.py
pvlv_commando/manual/__init__.py
pvlv_commando/manual/manual.json
pvlv_commando/manual/manual.py
pvlv_commando/manual/translations/__init__.py
pvlv_commando/manual/translations/manual_reply.py
pvlv_commando/replyes/__init__.py
pvlv_commando/replyes/errors_replies.py
pvlv_commando/replyes/permissions_replies.py