Metadata-Version: 2.1
Name: pvlv-commando
Version: 0.0.6
Summary: Command handler for Pavlov
Home-page: https://github.com/The-Pavlov-Project/Pavlov-Commando
Author: AbbestiaDC
Author-email: not.simone.scuola@outlook.com
License: LGPLv3
Platform: UNKNOWN
Classifier: Programming Language :: Python
Classifier: License :: OSI Approved :: GNU General Public License v3 (GPLv3)
Requires-Python: >=3.6
